<?xml version="1.0" encoding="UTF-8" ?>
<XMLDB PATH="local/udemysync/db" VERSION="20120122" COMMENT="XMLDB file for Moodle local/users"
    xmlns:xsi="http://www.w3.org/2001/XMLSchema-instance"
    xsi:noNamespaceSchemaLocation="../../../lib/xmldb/xmldb.xsd">
  <TABLES>
		<TABLE NAME="local_udemysync_modules" COMMENT="table holds errors caused during udemysync sync">
	        <FIELDS>
					<FIELD NAME="id" TYPE="int" LENGTH="10" NOTNULL="true" SEQUENCE="true"/>
					<FIELD NAME="module" TYPE="text" LENGTH="big" NOTNULL="false" SEQUENCE="false"/>
					<FIELD NAME="moduletype" TYPE="char" LENGTH="225" NOTNULL="false" SEQUENCE="false"/>
					<FIELD NAME="moduleid" TYPE="int" LENGTH="10" NOTNULL="false" SEQUENCE="false"/>
					<FIELD NAME="modulecrud" TYPE="char" LENGTH="225" NOTNULL="false" SEQUENCE="false"/>
					<FIELD NAME="status" TYPE="int" LENGTH="1" NOTNULL="false" SEQUENCE="false"/>
					<FIELD NAME="statusmessage" TYPE="text" NOTNULL="false" SEQUENCE="false"/>
					<FIELD NAME="timecreated" TYPE="int" LENGTH="10" NOTNULL="true" SEQUENCE="false"/>
					<FIELD NAME="usercreated" TYPE="int" LENGTH="10" NOTNULL="true" SEQUENCE="false"/>
					<FIELD NAME="timemodified" TYPE="int" LENGTH="10" NOTNULL="false" DEFAULT="0" SEQUENCE="false"/>
					<FIELD NAME="usermodified" TYPE="int" LENGTH="10" NOTNULL="false" DEFAULT="0" SEQUENCE="false"/>
			</FIELDS>
	      <KEYS>
	        <KEY NAME="primary" TYPE="primary" FIELDS="id"/>
	      </KEYS>
    	</TABLE>
  </TABLES>
</XMLDB>
